matlog/__init__.py
matlog/__version__.py
matlog/parser.py
matlog/tokens.py
matlog/utils.py
matlog-2.3.1.dist-info/LICENSE
matlog-2.3.1.dist-info/METADATA
matlog-2.3.1.dist-info/WHEEL
matlog-2.3.1.dist-info/top_level.txt
matlog-2.3.1.dist-info/RECORD
