Metadata-Version: 2.1
Name: matlog
Version: 2.3.1
Summary: matlog — Boolean Algebra Parser+Solver
Home-page: https://github.com/evtn/matlog
Author: evtn
Author-email: g@evtn.ru
License: GNUv3
Download-URL: https://github.com/evtn/matlog/archive/v2.3.1.tar.gz
Keywords: math mathematical logic boolean algebra
Platform: UNKNOWN
Classifier: Intended Audience :: Developers
Classifier: Programming Language :: Python :: 3
Classifier: Programming Language :: Python :: 3.6
Classifier: Programming Language :: Python :: 3.7
Classifier: Programming Language :: Python :: 3.8
Classifier: Programming Language :: Python :: 3.9
Requires-Python: >=3.6.*
Requires-Dist: lark
